[
  {
    "Id": "237820",
    "ThreadId": "69845",
    "Html": "<p>Hi,</p>\r\n<p>is there a way to enumerate pathes from a given source-sink-pair with ascending length? With the RankedShortestPath method, I have to give the number of pathes in advance - I would rather like to define some online termination criterion (for instance, path length above a threshold)</p>\r\n<p>Thanks for the Quickgraph package -it's really great work!</p>\r\n<p>&nbsp;</p>\r\n<p>--hier.</p>",
    "PostedDate": "2009-09-23T06:30:08.067-07:00",
    "UserRole": null,
    "MarkedAsAnswerDate": null
  }
]