{
  "WorkItem": {
    "AffectedComponent": {
      "Name": "",
      "DisplayName": ""
    },
    "ClosedComment": "",
    "ClosedDate": "2011-11-15T11:13:15.73-08:00",
    "CommentCount": 0,
    "Custom": null,
    "Description": "Hello! I use BreadthFirstSearchAlgorithm in QuickGraph 3.0. Traverse on my graph (see attached picture) is incorrect.\nI use events TreeEdge and NonTreeEdge. I have edges in order 1-2-5-3-6-4 instead 1-2-5-3-4-6.\n \nThank you.",
    "LastUpdatedDate": "2013-05-16T04:59:14.99-07:00",
    "PlannedForRelease": "",
    "ReleaseVisibleToPublic": false,
    "Priority": {
      "Name": "Low",
      "Severity": 50,
      "Id": 1
    },
    "ProjectName": "quickgraph",
    "ReportedDate": "2011-03-30T06:06:47.783-07:00",
    "Status": {
      "Name": "Closed",
      "Id": 4
    },
    "ReasonClosed": {
      "Name": "Unassigned"
    },
    "Summary": "Incorrect traversal of the graph (BreadthFirstSearchAlgorithm)",
    "Type": {
      "Name": "Issue",
      "Id": 3
    },
    "VoteCount": 1,
    "Id": 20360
  },
  "FileAttachments": [
    {
      "FileId": 4777,
      "FileName": "BFS.png",
      "DownloadUrl": ".\\4777"
    }
  ],
  "Comments": [
    {
      "Message": "I believe 1-2-5-3-6-4 is correct. Vertices B and D are at the same depth from root thus you receive their ancestors in succession and the correct order is 3-6. Then the last vertex is E, which is connected by edge 4.",
      "PostedDate": "2011-05-22T08:45:13.11-07:00",
      "Id": -2147483648
    },
    {
      "Message": "I checked your graph and I agree with filipnavara, 1-2-5-3-6-4 is the correct traversal.",
      "PostedDate": "2011-08-25T19:14:44.523-07:00",
      "Id": -2147483648
    },
    {
      "Message": "The order happens as expected. BFS is implemented with a FIFO queue so this ordering matches the traditional definition of this algorithm. Edge 6 is pushed on the queue when state D is visited (after edge 5). This happens before edge 4 is pushed in the queue. Thus, 4 is the last edge.",
      "PostedDate": "2011-11-15T11:13:08.4-08:00",
      "Id": -2147483648
    },
    {
      "Message": "",
      "PostedDate": "2011-11-15T11:13:15.73-08:00",
      "Id": -2147483648
    },
    {
      "Message": "",
      "PostedDate": "2013-02-21T17:44:38.81-08:00",
      "Id": -2147483648
    },
    {
      "Message": "",
      "PostedDate": "2013-05-16T04:59:14.99-07:00",
      "Id": -2147483648
    }
  ]
}